[
    {
        "text": "First Question First Answer",
        "questionId": "5fa6ba71c0d15708f2bfbe4c"
    },
    {
        "text": "First Question Second Answer",
        "questionId": "5fa6ba71c0d15708f2bfbe4c"
    },
    {
        "text": "First Question Third Answer",
        "questionId": "5fa6ba71c0d15708f2bfbe4c"
    },
    {
        "text": "Second Question First Answer",
        "questionId": "5fa6ba71c0d15708f2bfbe4d"
    },
    {
        "text": "Second Question Second Answer",
        "questionId": "5fa6ba71c0d15708f2bfbe4d"
    },
    {
        "text": "Third Question First Answer",
        "questionId": "5fa6ba71c0d15708f2bfbe4e"
    },
    {
        "text": "Fourth Question First Answer",
        "questionId": "5fa6ba71c0d15708f2bfbe4f"
    },
    {
        "text": "Fifth Question First Answer",
        "questionId": "5fa6ba71c0d15708f2bfbe50"
    }
]